{
  "$schema": "https://json-schema.org/draft/2020-12/schema",
  "$id": "#/definitions/OW5000_DlsSurfaceLocation",
  "title": "OW5000.DlsSurfaceLocation",
  "type": "object",
  "properties": {
    "well_location_id": {
      "type": "string",
      "maxLength": 12,
      "sqlType": "DBAPITYPEOBJECT('CHAR', 'NCHAR', 'NVARCHAR', 'VARCHAR', 'OTHER')"
    },
    "loc_exception": {
      "type": "string",
      "maxLength": 2,
      "sqlType": "DBAPITYPEOBJECT('CHAR', 'NCHAR', 'NVARCHAR', 'VARCHAR', 'OTHER')"
    },
    "event_sequence": {
      "type": "string",
      "maxLength": 1,
      "sqlType": "DBAPITYPEOBJECT('CHAR', 'NCHAR', 'NVARCHAR', 'VARCHAR', 'OTHER')"
    },
    "meridian": {
      "type": "string",
      "maxLength": 2,
      "sqlType": "DBAPITYPEOBJECT('CHAR', 'NCHAR', 'NVARCHAR', 'VARCHAR', 'OTHER')"
    },
    "meridian_dir": {
      "type": "string",
      "maxLength": 1,
      "sqlType": "DBAPITYPEOBJECT('CHAR', 'NCHAR', 'NVARCHAR', 'VARCHAR', 'OTHER')"
    },
    "rng_no": {
      "type": "string",
      "maxLength": 2,
      "sqlType": "DBAPITYPEOBJECT('CHAR', 'NCHAR', 'NVARCHAR', 'VARCHAR', 'OTHER')"
    },
    "rng_mod": {
      "type": "string",
      "maxLength": 1,
      "sqlType": "DBAPITYPEOBJECT('CHAR', 'NCHAR', 'NVARCHAR', 'VARCHAR', 'OTHER')"
    },
    "twp_no": {
      "type": "string",
      "maxLength": 3,
      "sqlType": "DBAPITYPEOBJECT('CHAR', 'NCHAR', 'NVARCHAR', 'VARCHAR', 'OTHER')"
    },
    "twp_mod": {
      "type": "string",
      "maxLength": 1,
      "sqlType": "DBAPITYPEOBJECT('CHAR', 'NCHAR', 'NVARCHAR', 'VARCHAR', 'OTHER')"
    },
    "sec": {
      "type": "string",
      "maxLength": 2,
      "sqlType": "DBAPITYPEOBJECT('CHAR', 'NCHAR', 'NVARCHAR', 'VARCHAR', 'OTHER')"
    },
    "subdivision": {
      "type": "string",
      "maxLength": 2,
      "sqlType": "DBAPITYPEOBJECT('CHAR', 'NCHAR', 'NVARCHAR', 'VARCHAR', 'OTHER')"
    },
    "remark": {
      "type": "string",
      "maxLength": 2000,
      "sqlType": "DBAPITYPEOBJECT('CHAR', 'NCHAR', 'NVARCHAR', 'VARCHAR', 'OTHER')"
    },
    "data_source": {
      "type": "string",
      "maxLength": 5,
      "sqlType": "DBAPITYPEOBJECT('CHAR', 'NCHAR', 'NVARCHAR', 'VARCHAR', 'OTHER')"
    },
    "create_date": {
      "type": "string",
      "format": "time",
      "maxLength": 29,
      "sqlType": "DBAPITYPEOBJECT('TIMESTAMP')"
    },
    "create_user_id": {
      "type": "string",
      "maxLength": 32,
      "sqlType": "DBAPITYPEOBJECT('CHAR', 'NCHAR', 'NVARCHAR', 'VARCHAR', 'OTHER')"
    },
    "update_date": {
      "type": "string",
      "format": "time",
      "maxLength": 29,
      "sqlType": "DBAPITYPEOBJECT('TIMESTAMP')"
    },
    "update_user_id": {
      "type": "string",
      "maxLength": 32,
      "sqlType": "DBAPITYPEOBJECT('CHAR', 'NCHAR', 'NVARCHAR', 'VARCHAR', 'OTHER')"
    },
    "row_lock_ind": {
      "type": "string",
      "maxLength": 1,
      "sqlType": "DBAPITYPEOBJECT('CHAR', 'NCHAR', 'NVARCHAR', 'VARCHAR', 'OTHER')"
    },
    "native_uid": {
      "type": "string",
      "maxLength": 4000,
      "sqlType": "DBAPITYPEOBJECT('CHAR', 'NCHAR', 'NVARCHAR', 'VARCHAR', 'OTHER')"
    }
  },
  "required": [
    "well_location_id"
  ]
}