{
  "$schema": "https://json-schema.org/draft/2020-12/schema",
  "$id": "#/definitions/OW5000_LoggingJob",
  "title": "OW5000.LoggingJob",
  "type": "object",
  "properties": {
    "wellid": {
      "type": "string",
      "maxLength": 31,
      "sqlType": "DBAPITYPEOBJECT('CHAR', 'NCHAR', 'NVARCHAR', 'VARCHAR', 'OTHER')"
    },
    "logging_job_no": {
      "type": "integer",
      "sqlType": "DBAPITYPEOBJECT('BOOLEAN', 'BIGINT', 'BIT', 'INTEGER', 'SMALLINT', 'TINYINT')"
    },
    "data_source": {
      "type": "string",
      "maxLength": 5,
      "sqlType": "DBAPITYPEOBJECT('CHAR', 'NCHAR', 'NVARCHAR', 'VARCHAR', 'OTHER')"
    },
    "acquisition_job_no": {
      "type": "string",
      "maxLength": 12,
      "sqlType": "DBAPITYPEOBJECT('CHAR', 'NCHAR', 'NVARCHAR', 'VARCHAR', 'OTHER')"
    },
    "company": {
      "type": "string",
      "maxLength": 40,
      "sqlType": "DBAPITYPEOBJECT('CHAR', 'NCHAR', 'NVARCHAR', 'VARCHAR', 'OTHER')"
    },
    "company_location": {
      "type": "string",
      "maxLength": 12,
      "sqlType": "DBAPITYPEOBJECT('CHAR', 'NCHAR', 'NVARCHAR', 'VARCHAR', 'OTHER')"
    },
    "equipment_type": {
      "type": "string",
      "maxLength": 12,
      "sqlType": "DBAPITYPEOBJECT('CHAR', 'NCHAR', 'NVARCHAR', 'VARCHAR', 'OTHER')"
    },
    "job_date": {
      "type": "string",
      "format": "time",
      "maxLength": 29,
      "sqlType": "DBAPITYPEOBJECT('TIMESTAMP')"
    },
    "datum_type": {
      "type": "string",
      "maxLength": 2,
      "sqlType": "DBAPITYPEOBJECT('CHAR', 'NCHAR', 'NVARCHAR', 'VARCHAR', 'OTHER')"
    },
    "permanent_datum_type": {
      "type": "string",
      "maxLength": 2,
      "sqlType": "DBAPITYPEOBJECT('CHAR', 'NCHAR', 'NVARCHAR', 'VARCHAR', 'OTHER')"
    },
    "drillers_datum_type": {
      "type": "string",
      "maxLength": 2,
      "sqlType": "DBAPITYPEOBJECT('CHAR', 'NCHAR', 'NVARCHAR', 'VARCHAR', 'OTHER')"
    },
    "elevation": {
      "type": "number",
      "format": "float",
      "multipleOf": 0.01,
      "sqlType": "DBAPITYPEOBJECT('FLOAT', 'REAL', 'DOUBLE')"
    },
    "elevation_dsdsunit": {
      "type": "string",
      "maxLength": 64,
      "sqlType": "DBAPITYPEOBJECT('CHAR', 'NCHAR', 'NVARCHAR', 'VARCHAR', 'OTHER')"
    },
    "circ_stopped_time": {
      "type": "string",
      "format": "time",
      "maxLength": 29,
      "sqlType": "DBAPITYPEOBJECT('TIMESTAMP')"
    },
    "hole_fluid_level": {
      "type": "number",
      "format": "float",
      "multipleOf": 0.01,
      "sqlType": "DBAPITYPEOBJECT('FLOAT', 'REAL', 'DOUBLE')"
    },
    "hole_fluid_level_dsdsunit": {
      "type": "string",
      "maxLength": 64,
      "sqlType": "DBAPITYPEOBJECT('CHAR', 'NCHAR', 'NVARCHAR', 'VARCHAR', 'OTHER')"
    },
    "casing_size": {
      "type": "number",
      "format": "float",
      "multipleOf": 1e-05,
      "sqlType": "DBAPITYPEOBJECT('FLOAT', 'REAL', 'DOUBLE')"
    },
    "casing_size_dsdsunit": {
      "type": "string",
      "maxLength": 64,
      "sqlType": "DBAPITYPEOBJECT('CHAR', 'NCHAR', 'NVARCHAR', 'VARCHAR', 'OTHER')"
    },
    "casing_weight": {
      "type": "number",
      "format": "float",
      "multipleOf": 1e-05,
      "sqlType": "DBAPITYPEOBJECT('FLOAT', 'REAL', 'DOUBLE')"
    },
    "casing_weight_dsdsunit": {
      "type": "string",
      "maxLength": 64,
      "sqlType": "DBAPITYPEOBJECT('CHAR', 'NCHAR', 'NVARCHAR', 'VARCHAR', 'OTHER')"
    },
    "casing_shoe_driller": {
      "type": "number",
      "format": "float",
      "multipleOf": 1e-05,
      "sqlType": "DBAPITYPEOBJECT('FLOAT', 'REAL', 'DOUBLE')"
    },
    "casing_shoe_driller_dsdsunit": {
      "type": "string",
      "maxLength": 64,
      "sqlType": "DBAPITYPEOBJECT('CHAR', 'NCHAR', 'NVARCHAR', 'VARCHAR', 'OTHER')"
    },
    "casing_shoe_depth": {
      "type": "number",
      "format": "float",
      "multipleOf": 0.01,
      "sqlType": "DBAPITYPEOBJECT('FLOAT', 'REAL', 'DOUBLE')"
    },
    "casing_shoe_depth_dsdsunit": {
      "type": "string",
      "maxLength": 64,
      "sqlType": "DBAPITYPEOBJECT('CHAR', 'NCHAR', 'NVARCHAR', 'VARCHAR', 'OTHER')"
    },
    "planned_top": {
      "type": "number",
      "format": "float",
      "multipleOf": 0.01,
      "sqlType": "DBAPITYPEOBJECT('FLOAT', 'REAL', 'DOUBLE')"
    },
    "planned_top_dsdsunit": {
      "type": "string",
      "maxLength": 64,
      "sqlType": "DBAPITYPEOBJECT('CHAR', 'NCHAR', 'NVARCHAR', 'VARCHAR', 'OTHER')"
    },
    "planned_base": {
      "type": "number",
      "format": "float",
      "multipleOf": 0.01,
      "sqlType": "DBAPITYPEOBJECT('FLOAT', 'REAL', 'DOUBLE')"
    },
    "planned_base_dsdsunit": {
      "type": "string",
      "maxLength": 64,
      "sqlType": "DBAPITYPEOBJECT('CHAR', 'NCHAR', 'NVARCHAR', 'VARCHAR', 'OTHER')"
    },
    "hole_diameter": {
      "type": "number",
      "format": "float",
      "multipleOf": 0.0001,
      "sqlType": "DBAPITYPEOBJECT('FLOAT', 'REAL', 'DOUBLE')"
    },
    "hole_diameter_dsdsunit": {
      "type": "string",
      "maxLength": 64,
      "sqlType": "DBAPITYPEOBJECT('CHAR', 'NCHAR', 'NVARCHAR', 'VARCHAR', 'OTHER')"
    },
    "driller_td": {
      "type": "number",
      "format": "float",
      "multipleOf": 0.01,
      "sqlType": "DBAPITYPEOBJECT('FLOAT', 'REAL', 'DOUBLE')"
    },
    "driller_td_dsdsunit": {
      "type": "string",
      "maxLength": 64,
      "sqlType": "DBAPITYPEOBJECT('CHAR', 'NCHAR', 'NVARCHAR', 'VARCHAR', 'OTHER')"
    },
    "logger_td": {
      "type": "number",
      "format": "float",
      "multipleOf": 0.01,
      "sqlType": "DBAPITYPEOBJECT('FLOAT', 'REAL', 'DOUBLE')"
    },
    "logger_td_dsdsunit": {
      "type": "string",
      "maxLength": 64,
      "sqlType": "DBAPITYPEOBJECT('CHAR', 'NCHAR', 'NVARCHAR', 'VARCHAR', 'OTHER')"
    },
    "witness_name": {
      "type": "string",
      "maxLength": 30,
      "sqlType": "DBAPITYPEOBJECT('CHAR', 'NCHAR', 'NVARCHAR', 'VARCHAR', 'OTHER')"
    },
    "logger_name": {
      "type": "string",
      "maxLength": 30,
      "sqlType": "DBAPITYPEOBJECT('CHAR', 'NCHAR', 'NVARCHAR', 'VARCHAR', 'OTHER')"
    },
    "logging_cost": {
      "type": "number",
      "format": "float",
      "multipleOf": 0.001,
      "sqlType": "DBAPITYPEOBJECT('FLOAT', 'REAL', 'DOUBLE')"
    },
    "standby_cost": {
      "type": "number",
      "format": "float",
      "multipleOf": 0.001,
      "sqlType": "DBAPITYPEOBJECT('FLOAT', 'REAL', 'DOUBLE')"
    },
    "projected_cost": {
      "type": "number",
      "format": "float",
      "multipleOf": 0.001,
      "sqlType": "DBAPITYPEOBJECT('FLOAT', 'REAL', 'DOUBLE')"
    },
    "total_cost": {
      "type": "number",
      "format": "float",
      "multipleOf": 0.001,
      "sqlType": "DBAPITYPEOBJECT('FLOAT', 'REAL', 'DOUBLE')"
    },
    "misc_cost": {
      "type": "number",
      "format": "float",
      "multipleOf": 0.001,
      "sqlType": "DBAPITYPEOBJECT('FLOAT', 'REAL', 'DOUBLE')"
    },
    "logging_hours": {
      "type": "number",
      "format": "float",
      "multipleOf": 0.001,
      "sqlType": "DBAPITYPEOBJECT('FLOAT', 'REAL', 'DOUBLE')"
    },
    "logging_hours_dsdsunit": {
      "type": "string",
      "maxLength": 64,
      "sqlType": "DBAPITYPEOBJECT('CHAR', 'NCHAR', 'NVARCHAR', 'VARCHAR', 'OTHER')"
    },
    "wiper_trips": {
      "type": "integer",
      "sqlType": "DBAPITYPEOBJECT('BOOLEAN', 'BIGINT', 'BIT', 'INTEGER', 'SMALLINT', 'TINYINT')"
    },
    "downtime": {
      "type": "number",
      "format": "float",
      "multipleOf": 0.001,
      "sqlType": "DBAPITYPEOBJECT('FLOAT', 'REAL', 'DOUBLE')"
    },
    "downtime_dsdsunit": {
      "type": "string",
      "maxLength": 64,
      "sqlType": "DBAPITYPEOBJECT('CHAR', 'NCHAR', 'NVARCHAR', 'VARCHAR', 'OTHER')"
    },
    "time_since_circ": {
      "type": "number",
      "format": "float",
      "multipleOf": 0.001,
      "sqlType": "DBAPITYPEOBJECT('FLOAT', 'REAL', 'DOUBLE')"
    },
    "time_since_circ_dsdsunit": {
      "type": "string",
      "maxLength": 64,
      "sqlType": "DBAPITYPEOBJECT('CHAR', 'NCHAR', 'NVARCHAR', 'VARCHAR', 'OTHER')"
    },
    "reason_down": {
      "type": "string",
      "maxLength": 40,
      "sqlType": "DBAPITYPEOBJECT('CHAR', 'NCHAR', 'NVARCHAR', 'VARCHAR', 'OTHER')"
    },
    "remark": {
      "type": "string",
      "maxLength": 2000,
      "sqlType": "DBAPITYPEOBJECT('CHAR', 'NCHAR', 'NVARCHAR', 'VARCHAR', 'OTHER')"
    },
    "currency": {
      "type": "string",
      "maxLength": 24,
      "sqlType": "DBAPITYPEOBJECT('CHAR', 'NCHAR', 'NVARCHAR', 'VARCHAR', 'OTHER')"
    },
    "create_user_id": {
      "type": "string",
      "maxLength": 32,
      "sqlType": "DBAPITYPEOBJECT('CHAR', 'NCHAR', 'NVARCHAR', 'VARCHAR', 'OTHER')"
    },
    "create_date": {
      "type": "string",
      "format": "time",
      "maxLength": 29,
      "sqlType": "DBAPITYPEOBJECT('TIMESTAMP')"
    },
    "update_user_id": {
      "type": "string",
      "maxLength": 32,
      "sqlType": "DBAPITYPEOBJECT('CHAR', 'NCHAR', 'NVARCHAR', 'VARCHAR', 'OTHER')"
    },
    "update_date": {
      "type": "string",
      "format": "time",
      "maxLength": 29,
      "sqlType": "DBAPITYPEOBJECT('TIMESTAMP')"
    },
    "row_lock_ind": {
      "type": "string",
      "maxLength": 1,
      "sqlType": "DBAPITYPEOBJECT('CHAR', 'NCHAR', 'NVARCHAR', 'VARCHAR', 'OTHER')"
    },
    "native_uid": {
      "type": "string",
      "maxLength": 4000,
      "sqlType": "DBAPITYPEOBJECT('CHAR', 'NCHAR', 'NVARCHAR', 'VARCHAR', 'OTHER')"
    }
  }
}