{
  "$schema": "https://json-schema.org/draft/2020-12/schema",
  "$id": "#/definitions/OW5000_Tubing",
  "title": "OW5000.Tubing",
  "type": "object",
  "properties": {
    "wellid": {
      "type": "string",
      "maxLength": 31,
      "sqlType": "DBAPITYPEOBJECT('CHAR', 'NCHAR', 'NVARCHAR', 'VARCHAR', 'OTHER')"
    },
    "tubing_set_depth": {
      "type": "number",
      "format": "float",
      "multipleOf": 0.01,
      "sqlType": "DBAPITYPEOBJECT('FLOAT', 'REAL', 'DOUBLE')"
    },
    "tubing_set_depth_dsdsunit": {
      "type": "string",
      "maxLength": 64,
      "sqlType": "DBAPITYPEOBJECT('CHAR', 'NCHAR', 'NVARCHAR', 'VARCHAR', 'OTHER')"
    },
    "tubing_string_no": {
      "type": "integer",
      "sqlType": "DBAPITYPEOBJECT('BOOLEAN', 'BIGINT', 'BIT', 'INTEGER', 'SMALLINT', 'TINYINT')"
    },
    "data_source": {
      "type": "string",
      "maxLength": 5,
      "sqlType": "DBAPITYPEOBJECT('CHAR', 'NCHAR', 'NVARCHAR', 'VARCHAR', 'OTHER')"
    },
    "formation": {
      "type": "string",
      "maxLength": 255,
      "sqlType": "DBAPITYPEOBJECT('CHAR', 'NCHAR', 'NVARCHAR', 'VARCHAR', 'OTHER')"
    },
    "tubing_install_dte": {
      "type": "string",
      "format": "time",
      "maxLength": 29,
      "sqlType": "DBAPITYPEOBJECT('TIMESTAMP')"
    },
    "tubing_remove_dte": {
      "type": "string",
      "format": "time",
      "maxLength": 29,
      "sqlType": "DBAPITYPEOBJECT('TIMESTAMP')"
    },
    "tubing_size": {
      "type": "number",
      "format": "float",
      "multipleOf": 0.0001,
      "sqlType": "DBAPITYPEOBJECT('FLOAT', 'REAL', 'DOUBLE')"
    },
    "tubing_size_dsdsunit": {
      "type": "string",
      "maxLength": 64,
      "sqlType": "DBAPITYPEOBJECT('CHAR', 'NCHAR', 'NVARCHAR', 'VARCHAR', 'OTHER')"
    },
    "remark": {
      "type": "string",
      "maxLength": 2000,
      "sqlType": "DBAPITYPEOBJECT('CHAR', 'NCHAR', 'NVARCHAR', 'VARCHAR', 'OTHER')"
    },
    "create_date": {
      "type": "string",
      "format": "time",
      "maxLength": 29,
      "sqlType": "DBAPITYPEOBJECT('TIMESTAMP')"
    },
    "create_user_id": {
      "type": "string",
      "maxLength": 32,
      "sqlType": "DBAPITYPEOBJECT('CHAR', 'NCHAR', 'NVARCHAR', 'VARCHAR', 'OTHER')"
    },
    "update_date": {
      "type": "string",
      "format": "time",
      "maxLength": 29,
      "sqlType": "DBAPITYPEOBJECT('TIMESTAMP')"
    },
    "update_user_id": {
      "type": "string",
      "maxLength": 32,
      "sqlType": "DBAPITYPEOBJECT('CHAR', 'NCHAR', 'NVARCHAR', 'VARCHAR', 'OTHER')"
    },
    "row_lock_ind": {
      "type": "string",
      "maxLength": 1,
      "sqlType": "DBAPITYPEOBJECT('CHAR', 'NCHAR', 'NVARCHAR', 'VARCHAR', 'OTHER')"
    },
    "native_uid": {
      "type": "string",
      "maxLength": 4000,
      "sqlType": "DBAPITYPEOBJECT('CHAR', 'NCHAR', 'NVARCHAR', 'VARCHAR', 'OTHER')"
    }
  },
  "required": [
    "wellid",
    "tubing_set_depth",
    "tubing_set_depth_dsdsunit",
    "tubing_string_no"
  ]
}