{
  "$schema": "https://json-schema.org/draft/2020-12/schema",
  "$id": "#/definitions/OW5000_LogSampleBlockInfo",
  "title": "OW5000.LogSampleBlockInfo",
  "type": "object",
  "properties": {
    "log_curve_id": {
      "type": "integer",
      "sqlType": "DBAPITYPEOBJECT('BOOLEAN', 'BIGINT', 'BIT', 'INTEGER', 'SMALLINT', 'TINYINT')"
    },
    "vid": {
      "type": "integer",
      "sqlType": "DBAPITYPEOBJECT('BOOLEAN', 'BIGINT', 'BIT', 'INTEGER', 'SMALLINT', 'TINYINT')"
    },
    "blk_no": {
      "type": "integer",
      "sqlType": "DBAPITYPEOBJECT('BOOLEAN', 'BIGINT', 'BIT', 'INTEGER', 'SMALLINT', 'TINYINT')"
    },
    "first_sample_num": {
      "type": "integer",
      "sqlType": "DBAPITYPEOBJECT('BOOLEAN', 'BIGINT', 'BIT', 'INTEGER', 'SMALLINT', 'TINYINT')"
    },
    "last_sample_num": {
      "type": "integer",
      "sqlType": "DBAPITYPEOBJECT('BOOLEAN', 'BIGINT', 'BIT', 'INTEGER', 'SMALLINT', 'TINYINT')"
    },
    "block_size": {
      "type": "integer",
      "sqlType": "DBAPITYPEOBJECT('BOOLEAN', 'BIGINT', 'BIT', 'INTEGER', 'SMALLINT', 'TINYINT')"
    },
    "native_uid": {
      "type": "string",
      "maxLength": 4000,
      "sqlType": "DBAPITYPEOBJECT('CHAR', 'NCHAR', 'NVARCHAR', 'VARCHAR', 'OTHER')"
    }
  },
  "required": [
    "log_curve_id",
    "vid",
    "blk_no",
    "first_sample_num",
    "last_sample_num",
    "block_size"
  ]
}