{
  "$schema": "https://json-schema.org/draft/2020-12/schema",
  "$id": "#/definitions/OW5000_ISetDataObject",
  "title": "OW5000.ISetDataObject",
  "type": "object",
  "properties": {
    "interpretation_set_id": {
      "type": "string",
      "maxLength": 12,
      "sqlType": "DBAPITYPEOBJECT('CHAR', 'NCHAR', 'NVARCHAR', 'VARCHAR', 'OTHER')"
    },
    "iset_folder_id": {
      "type": "integer",
      "sqlType": "DBAPITYPEOBJECT('BOOLEAN', 'BIGINT', 'BIT', 'INTEGER', 'SMALLINT', 'TINYINT')"
    },
    "data_key": {
      "type": "string",
      "maxLength": 1500,
      "sqlType": "DBAPITYPEOBJECT('CHAR', 'NCHAR', 'NVARCHAR', 'VARCHAR', 'OTHER')"
    },
    "data_type": {
      "type": "string",
      "maxLength": 40,
      "sqlType": "DBAPITYPEOBJECT('CHAR', 'NCHAR', 'NVARCHAR', 'VARCHAR', 'OTHER')"
    },
    "data_object_name": {
      "type": "string",
      "maxLength": 80,
      "sqlType": "DBAPITYPEOBJECT('CHAR', 'NCHAR', 'NVARCHAR', 'VARCHAR', 'OTHER')"
    },
    "data_object_id": {
      "type": "integer",
      "sqlType": "DBAPITYPEOBJECT('BOOLEAN', 'BIGINT', 'BIT', 'INTEGER', 'SMALLINT', 'TINYINT')"
    },
    "remark": {
      "type": "string",
      "maxLength": 2000,
      "sqlType": "DBAPITYPEOBJECT('CHAR', 'NCHAR', 'NVARCHAR', 'VARCHAR', 'OTHER')"
    },
    "create_user_id": {
      "type": "string",
      "maxLength": 32,
      "sqlType": "DBAPITYPEOBJECT('CHAR', 'NCHAR', 'NVARCHAR', 'VARCHAR', 'OTHER')"
    },
    "create_date": {
      "type": "string",
      "format": "time",
      "maxLength": 29,
      "sqlType": "DBAPITYPEOBJECT('TIMESTAMP')"
    },
    "update_user_id": {
      "type": "string",
      "maxLength": 32,
      "sqlType": "DBAPITYPEOBJECT('CHAR', 'NCHAR', 'NVARCHAR', 'VARCHAR', 'OTHER')"
    },
    "update_date": {
      "type": "string",
      "format": "time",
      "maxLength": 29,
      "sqlType": "DBAPITYPEOBJECT('TIMESTAMP')"
    },
    "native_uid": {
      "type": "string",
      "maxLength": 4000,
      "sqlType": "DBAPITYPEOBJECT('CHAR', 'NCHAR', 'NVARCHAR', 'VARCHAR', 'OTHER')"
    }
  },
  "required": [
    "interpretation_set_id",
    "iset_folder_id",
    "data_key",
    "data_type"
  ]
}