{
  "$schema": "https://json-schema.org/draft/2020-12/schema",
  "$id": "#/definitions/OW5000_LogCurveStructured",
  "title": "OW5000.LogCurveStructured",
  "type": "object",
  "properties": {
    "wellid": {
      "type": "string",
      "maxLength": 31,
      "sqlType": "DBAPITYPEOBJECT('CHAR', 'NCHAR', 'NVARCHAR', 'VARCHAR', 'OTHER')"
    },
    "log_crv_name": {
      "type": "string",
      "maxLength": 25,
      "sqlType": "DBAPITYPEOBJECT('CHAR', 'NCHAR', 'NVARCHAR', 'VARCHAR', 'OTHER')"
    },
    "log_run_no": {
      "type": "integer",
      "sqlType": "DBAPITYPEOBJECT('BOOLEAN', 'BIGINT', 'BIT', 'INTEGER', 'SMALLINT', 'TINYINT')"
    },
    "log_crv_version": {
      "type": "integer",
      "sqlType": "DBAPITYPEOBJECT('BOOLEAN', 'BIGINT', 'BIT', 'INTEGER', 'SMALLINT', 'TINYINT')"
    },
    "log_curve_id": {
      "type": "string",
      "maxLength": 3,
      "sqlType": "DBAPITYPEOBJECT('CHAR', 'NCHAR', 'NVARCHAR', 'VARCHAR', 'OTHER')"
    },
    "framework_obs_no": {
      "type": "integer",
      "sqlType": "DBAPITYPEOBJECT('BOOLEAN', 'BIGINT', 'BIT', 'INTEGER', 'SMALLINT', 'TINYINT')"
    },
    "creating_anal_id": {
      "type": "string",
      "maxLength": 12,
      "sqlType": "DBAPITYPEOBJECT('CHAR', 'NCHAR', 'NVARCHAR', 'VARCHAR', 'OTHER')"
    },
    "logging_job_no": {
      "type": "integer",
      "sqlType": "DBAPITYPEOBJECT('BOOLEAN', 'BIGINT', 'BIT', 'INTEGER', 'SMALLINT', 'TINYINT')"
    },
    "tool_code": {
      "type": "string",
      "maxLength": 12,
      "sqlType": "DBAPITYPEOBJECT('CHAR', 'NCHAR', 'NVARCHAR', 'VARCHAR', 'OTHER')"
    },
    "tool_position_seq_no": {
      "type": "integer",
      "sqlType": "DBAPITYPEOBJECT('BOOLEAN', 'BIGINT', 'BIT', 'INTEGER', 'SMALLINT', 'TINYINT')"
    },
    "log_pass_id": {
      "type": "string",
      "maxLength": 4,
      "sqlType": "DBAPITYPEOBJECT('CHAR', 'NCHAR', 'NVARCHAR', 'VARCHAR', 'OTHER')"
    },
    "log_name": {
      "type": "string",
      "maxLength": 30,
      "sqlType": "DBAPITYPEOBJECT('CHAR', 'NCHAR', 'NVARCHAR', 'VARCHAR', 'OTHER')"
    },
    "data_source": {
      "type": "string",
      "maxLength": 5,
      "sqlType": "DBAPITYPEOBJECT('CHAR', 'NCHAR', 'NVARCHAR', 'VARCHAR', 'OTHER')"
    },
    "original_data_source": {
      "type": "string",
      "maxLength": 5,
      "sqlType": "DBAPITYPEOBJECT('CHAR', 'NCHAR', 'NVARCHAR', 'VARCHAR', 'OTHER')"
    },
    "storage_id": {
      "type": "string",
      "maxLength": 12,
      "sqlType": "DBAPITYPEOBJECT('CHAR', 'NCHAR', 'NVARCHAR', 'VARCHAR', 'OTHER')"
    },
    "trace_storage_type": {
      "type": "string",
      "maxLength": 12,
      "sqlType": "DBAPITYPEOBJECT('CHAR', 'NCHAR', 'NVARCHAR', 'VARCHAR', 'OTHER')"
    },
    "trace_online_ind": {
      "type": "string",
      "maxLength": 1,
      "sqlType": "DBAPITYPEOBJECT('CHAR', 'NCHAR', 'NVARCHAR', 'VARCHAR', 'OTHER')"
    },
    "section": {
      "type": "string",
      "maxLength": 60,
      "sqlType": "DBAPITYPEOBJECT('CHAR', 'NCHAR', 'NVARCHAR', 'VARCHAR', 'OTHER')"
    },
    "block": {
      "type": "string",
      "maxLength": 60,
      "sqlType": "DBAPITYPEOBJECT('CHAR', 'NCHAR', 'NVARCHAR', 'VARCHAR', 'OTHER')"
    },
    "sub_block": {
      "type": "string",
      "maxLength": 60,
      "sqlType": "DBAPITYPEOBJECT('CHAR', 'NCHAR', 'NVARCHAR', 'VARCHAR', 'OTHER')"
    },
    "external_crv_name": {
      "type": "string",
      "maxLength": 25,
      "sqlType": "DBAPITYPEOBJECT('CHAR', 'NCHAR', 'NVARCHAR', 'VARCHAR', 'OTHER')"
    },
    "external_well_name": {
      "type": "string",
      "maxLength": 80,
      "sqlType": "DBAPITYPEOBJECT('CHAR', 'NCHAR', 'NVARCHAR', 'VARCHAR', 'OTHER')"
    },
    "total_samples": {
      "type": "integer",
      "sqlType": "DBAPITYPEOBJECT('BOOLEAN', 'BIGINT', 'BIT', 'INTEGER', 'SMALLINT', 'TINYINT')"
    },
    "storage_depth_units": {
      "type": "string",
      "maxLength": 12,
      "sqlType": "DBAPITYPEOBJECT('CHAR', 'NCHAR', 'NVARCHAR', 'VARCHAR', 'OTHER')"
    },
    "storage_depth_mode": {
      "type": "integer",
      "sqlType": "DBAPITYPEOBJECT('BOOLEAN', 'BIGINT', 'BIT', 'INTEGER', 'SMALLINT', 'TINYINT')"
    },
    "depth_mode": {
      "type": "integer",
      "sqlType": "DBAPITYPEOBJECT('BOOLEAN', 'BIGINT', 'BIT', 'INTEGER', 'SMALLINT', 'TINYINT')"
    },
    "log_crv_unit_meas": {
      "type": "string",
      "maxLength": 30,
      "sqlType": "DBAPITYPEOBJECT('CHAR', 'NCHAR', 'NVARCHAR', 'VARCHAR', 'OTHER')"
    },
    "access_mode": {
      "type": "string",
      "maxLength": 1,
      "sqlType": "DBAPITYPEOBJECT('CHAR', 'NCHAR', 'NVARCHAR', 'VARCHAR', 'OTHER')"
    },
    "top_depth": {
      "type": "number",
      "format": "float",
      "multipleOf": 0.001,
      "sqlType": "DBAPITYPEOBJECT('FLOAT', 'REAL', 'DOUBLE')"
    },
    "top_depth_dsdsunit": {
      "type": "string",
      "maxLength": 64,
      "sqlType": "DBAPITYPEOBJECT('CHAR', 'NCHAR', 'NVARCHAR', 'VARCHAR', 'OTHER')"
    },
    "base_depth": {
      "type": "number",
      "format": "float",
      "multipleOf": 0.001,
      "sqlType": "DBAPITYPEOBJECT('FLOAT', 'REAL', 'DOUBLE')"
    },
    "base_depth_dsdsunit": {
      "type": "string",
      "maxLength": 64,
      "sqlType": "DBAPITYPEOBJECT('CHAR', 'NCHAR', 'NVARCHAR', 'VARCHAR', 'OTHER')"
    },
    "crv_increm": {
      "type": "number",
      "format": "float",
      "multipleOf": 0.001,
      "sqlType": "DBAPITYPEOBJECT('FLOAT', 'REAL', 'DOUBLE')"
    },
    "crv_increm_dsdsunit": {
      "type": "string",
      "maxLength": 64,
      "sqlType": "DBAPITYPEOBJECT('CHAR', 'NCHAR', 'NVARCHAR', 'VARCHAR', 'OTHER')"
    },
    "min_value": {
      "type": "number",
      "format": "float",
      "multipleOf": 1e-05,
      "sqlType": "DBAPITYPEOBJECT('FLOAT', 'REAL', 'DOUBLE')"
    },
    "min_value_dsdsunit": {
      "type": "string",
      "maxLength": 64,
      "sqlType": "DBAPITYPEOBJECT('CHAR', 'NCHAR', 'NVARCHAR', 'VARCHAR', 'OTHER')"
    },
    "unit_type_id": {
      "type": "string",
      "maxLength": 64,
      "sqlType": "DBAPITYPEOBJECT('CHAR', 'NCHAR', 'NVARCHAR', 'VARCHAR', 'OTHER')"
    },
    "max_value": {
      "type": "number",
      "format": "float",
      "multipleOf": 1e-05,
      "sqlType": "DBAPITYPEOBJECT('FLOAT', 'REAL', 'DOUBLE')"
    },
    "max_value_dsdsunit": {
      "type": "string",
      "maxLength": 64,
      "sqlType": "DBAPITYPEOBJECT('CHAR', 'NCHAR', 'NVARCHAR', 'VARCHAR', 'OTHER')"
    },
    "storage_znon": {
      "type": "number",
      "format": "float",
      "multipleOf": 1e-05,
      "sqlType": "DBAPITYPEOBJECT('FLOAT', 'REAL', 'DOUBLE')"
    },
    "znon": {
      "type": "number",
      "format": "float",
      "multipleOf": 1e-05,
      "sqlType": "DBAPITYPEOBJECT('FLOAT', 'REAL', 'DOUBLE')"
    },
    "log_quality": {
      "type": "integer",
      "sqlType": "DBAPITYPEOBJECT('BOOLEAN', 'BIGINT', 'BIT', 'INTEGER', 'SMALLINT', 'TINYINT')"
    },
    "api_code": {
      "type": "string",
      "maxLength": 12,
      "sqlType": "DBAPITYPEOBJECT('CHAR', 'NCHAR', 'NVARCHAR', 'VARCHAR', 'OTHER')"
    },
    "storage_data_type": {
      "type": "string",
      "maxLength": 16,
      "sqlType": "DBAPITYPEOBJECT('CHAR', 'NCHAR', 'NVARCHAR', 'VARCHAR', 'OTHER')"
    },
    "char_data_ind": {
      "type": "string",
      "maxLength": 1,
      "sqlType": "DBAPITYPEOBJECT('CHAR', 'NCHAR', 'NVARCHAR', 'VARCHAR', 'OTHER')"
    },
    "value_storage_direction": {
      "type": "string",
      "maxLength": 11,
      "sqlType": "DBAPITYPEOBJECT('CHAR', 'NCHAR', 'NVARCHAR', 'VARCHAR', 'OTHER')"
    },
    "start_framework_sample_no": {
      "type": "integer",
      "sqlType": "DBAPITYPEOBJECT('BOOLEAN', 'BIGINT', 'BIT', 'INTEGER', 'SMALLINT', 'TINYINT')"
    },
    "end_framework_sample_no": {
      "type": "integer",
      "sqlType": "DBAPITYPEOBJECT('BOOLEAN', 'BIGINT', 'BIT', 'INTEGER', 'SMALLINT', 'TINYINT')"
    },
    "resampling_scheme": {
      "type": "string",
      "maxLength": 20,
      "sqlType": "DBAPITYPEOBJECT('CHAR', 'NCHAR', 'NVARCHAR', 'VARCHAR', 'OTHER')"
    },
    "number_of_dimensions": {
      "type": "integer",
      "sqlType": "DBAPITYPEOBJECT('BOOLEAN', 'BIGINT', 'BIT', 'INTEGER', 'SMALLINT', 'TINYINT')"
    },
    "second_dimension_npts": {
      "type": "integer",
      "sqlType": "DBAPITYPEOBJECT('BOOLEAN', 'BIGINT', 'BIT', 'INTEGER', 'SMALLINT', 'TINYINT')"
    },
    "second_dimension_start": {
      "type": "number",
      "format": "float",
      "multipleOf": 1e-05,
      "sqlType": "DBAPITYPEOBJECT('FLOAT', 'REAL', 'DOUBLE')"
    },
    "second_dimension_stop": {
      "type": "number",
      "format": "float",
      "multipleOf": 1e-05,
      "sqlType": "DBAPITYPEOBJECT('FLOAT', 'REAL', 'DOUBLE')"
    },
    "second_dimension_increment": {
      "type": "number",
      "format": "float",
      "multipleOf": 1e-05,
      "sqlType": "DBAPITYPEOBJECT('FLOAT', 'REAL', 'DOUBLE')"
    },
    "second_dimension_unit_type_id": {
      "type": "string",
      "maxLength": 12,
      "sqlType": "DBAPITYPEOBJECT('CHAR', 'NCHAR', 'NVARCHAR', 'VARCHAR', 'OTHER')"
    },
    "second_dimension_ouom": {
      "type": "string",
      "maxLength": 12,
      "sqlType": "DBAPITYPEOBJECT('CHAR', 'NCHAR', 'NVARCHAR', 'VARCHAR', 'OTHER')"
    },
    "second_dimension_working_uom": {
      "type": "string",
      "maxLength": 12,
      "sqlType": "DBAPITYPEOBJECT('CHAR', 'NCHAR', 'NVARCHAR', 'VARCHAR', 'OTHER')"
    },
    "second_dimension_unit_desc": {
      "type": "string",
      "maxLength": 30,
      "sqlType": "DBAPITYPEOBJECT('CHAR', 'NCHAR', 'NVARCHAR', 'VARCHAR', 'OTHER')"
    },
    "third_dimension_npts": {
      "type": "integer",
      "sqlType": "DBAPITYPEOBJECT('BOOLEAN', 'BIGINT', 'BIT', 'INTEGER', 'SMALLINT', 'TINYINT')"
    },
    "third_dimension_start": {
      "type": "number",
      "format": "float",
      "multipleOf": 1e-05,
      "sqlType": "DBAPITYPEOBJECT('FLOAT', 'REAL', 'DOUBLE')"
    },
    "third_dimension_stop": {
      "type": "number",
      "format": "float",
      "multipleOf": 1e-05,
      "sqlType": "DBAPITYPEOBJECT('FLOAT', 'REAL', 'DOUBLE')"
    },
    "third_dimension_increment": {
      "type": "number",
      "format": "float",
      "multipleOf": 1e-05,
      "sqlType": "DBAPITYPEOBJECT('FLOAT', 'REAL', 'DOUBLE')"
    },
    "third_dimension_unit_type_id": {
      "type": "string",
      "maxLength": 12,
      "sqlType": "DBAPITYPEOBJECT('CHAR', 'NCHAR', 'NVARCHAR', 'VARCHAR', 'OTHER')"
    },
    "third_dimension_ouom": {
      "type": "string",
      "maxLength": 12,
      "sqlType": "DBAPITYPEOBJECT('CHAR', 'NCHAR', 'NVARCHAR', 'VARCHAR', 'OTHER')"
    },
    "third_dimension_working_uom": {
      "type": "string",
      "maxLength": 12,
      "sqlType": "DBAPITYPEOBJECT('CHAR', 'NCHAR', 'NVARCHAR', 'VARCHAR', 'OTHER')"
    },
    "third_dimension_unit_desc": {
      "type": "string",
      "maxLength": 30,
      "sqlType": "DBAPITYPEOBJECT('CHAR', 'NCHAR', 'NVARCHAR', 'VARCHAR', 'OTHER')"
    },
    "remark": {
      "type": "string",
      "maxLength": 2000,
      "sqlType": "DBAPITYPEOBJECT('CHAR', 'NCHAR', 'NVARCHAR', 'VARCHAR', 'OTHER')"
    },
    "remarks_ind": {
      "type": "integer",
      "sqlType": "DBAPITYPEOBJECT('BOOLEAN', 'BIGINT', 'BIT', 'INTEGER', 'SMALLINT', 'TINYINT')"
    },
    "log_crv_alias": {
      "type": "string",
      "maxLength": 25,
      "sqlType": "DBAPITYPEOBJECT('CHAR', 'NCHAR', 'NVARCHAR', 'VARCHAR', 'OTHER')"
    },
    "create_date": {
      "type": "string",
      "format": "time",
      "maxLength": 29,
      "sqlType": "DBAPITYPEOBJECT('TIMESTAMP')"
    },
    "create_user_id": {
      "type": "string",
      "maxLength": 32,
      "sqlType": "DBAPITYPEOBJECT('CHAR', 'NCHAR', 'NVARCHAR', 'VARCHAR', 'OTHER')"
    },
    "creation_routine": {
      "type": "string",
      "maxLength": 10,
      "sqlType": "DBAPITYPEOBJECT('CHAR', 'NCHAR', 'NVARCHAR', 'VARCHAR', 'OTHER')"
    },
    "update_date": {
      "type": "string",
      "format": "time",
      "maxLength": 29,
      "sqlType": "DBAPITYPEOBJECT('TIMESTAMP')"
    },
    "update_user_id": {
      "type": "string",
      "maxLength": 32,
      "sqlType": "DBAPITYPEOBJECT('CHAR', 'NCHAR', 'NVARCHAR', 'VARCHAR', 'OTHER')"
    },
    "update_routine": {
      "type": "string",
      "maxLength": 10,
      "sqlType": "DBAPITYPEOBJECT('CHAR', 'NCHAR', 'NVARCHAR', 'VARCHAR', 'OTHER')"
    },
    "top_depth_storage": {
      "type": "number",
      "format": "float",
      "multipleOf": 1e-05,
      "sqlType": "DBAPITYPEOBJECT('FLOAT', 'REAL', 'DOUBLE')"
    },
    "base_depth_storage": {
      "type": "number",
      "format": "float",
      "multipleOf": 1e-05,
      "sqlType": "DBAPITYPEOBJECT('FLOAT', 'REAL', 'DOUBLE')"
    },
    "crv_increm_storage": {
      "type": "number",
      "format": "float",
      "multipleOf": 1e-05,
      "sqlType": "DBAPITYPEOBJECT('FLOAT', 'REAL', 'DOUBLE')"
    },
    "structured_count": {
      "type": "integer",
      "sqlType": "DBAPITYPEOBJECT('BOOLEAN', 'BIGINT', 'BIT', 'INTEGER', 'SMALLINT', 'TINYINT')"
    },
    "bulk_data_id": {
      "type": "integer",
      "sqlType": "DBAPITYPEOBJECT('BOOLEAN', 'BIGINT', 'BIT', 'INTEGER', 'SMALLINT', 'TINYINT')"
    },
    "row_lock_ind": {
      "type": "string",
      "maxLength": 1,
      "sqlType": "DBAPITYPEOBJECT('CHAR', 'NCHAR', 'NVARCHAR', 'VARCHAR', 'OTHER')"
    },
    "data": {
      "type": "string",
      "format": "binary",
      "maxLength": 2147483647,
      "sqlType": "DBAPITYPEOBJECT('BINARY', 'BLOB', 'LONGVARBINARY', 'VARBINARY')"
    },
    "native_uid": {
      "type": "string",
      "maxLength": 4000,
      "sqlType": "DBAPITYPEOBJECT('CHAR', 'NCHAR', 'NVARCHAR', 'VARCHAR', 'OTHER')"
    },
    "parent_native_uid": {
      "type": "string",
      "maxLength": 4000,
      "sqlType": "DBAPITYPEOBJECT('CHAR', 'NCHAR', 'NVARCHAR', 'VARCHAR', 'OTHER')"
    }
  },
  "required": [
    "wellid",
    "log_crv_name",
    "log_run_no",
    "log_crv_version",
    "log_curve_id",
    "log_pass_id",
    "log_name",
    "top_depth",
    "top_depth_dsdsunit",
    "base_depth",
    "base_depth_dsdsunit",
    "crv_increm"
  ]
}